
{
  "mods": 
  [
    
    {
      "name": "base",
      "enabled": true
    },
    
    {
      "name": "AutoDeconstruct",
      "enabled": true
    },
    
    {
      "name": "belt-visualizer",
      "enabled": true
    },
    
    {
      "name": "BotSpeed",
      "enabled": true
    },
    
    {
      "name": "BotStart",
      "enabled": true
    },
    
    {
      "name": "BottleneckLite",
      "enabled": true
    },
    
    {
      "name": "factoryplanner",
      "enabled": true
    },
    
    {
      "name": "flib",
      "enabled": true
    },
    
    {
      "name": "FNEI",
      "enabled": true
    },
    
    {
      "name": "helmod",
      "enabled": true
    },
    
    {
      "name": "InfiniteInventory",
      "enabled": true
    },
    
    {
      "name": "long-reach-clone",
      "enabled": true
    },
    
    {
      "name": "MaxRateCalculator",
      "enabled": true
    },
    
    {
      "name": "OutpostPlanner1-1",
      "enabled": true
    },
    
    {
      "name": "PlannerCore1-1",
      "enabled": true
    },
    
    {
      "name": "RailSignalPlanner",
      "enabled": true
    },
    
    {
      "name": "RateCalculator",
      "enabled": true
    },
    
    {
      "name": "Squeak Through",
      "enabled": true
    },
    
    {
      "name": "stdlib",
      "enabled": true
    },
    
    {
      "name": "TogglePeacefulMode",
      "enabled": true
    }
  ]
}
